[
  {"id":"photo1","thumb":"assets/webp/thumbs/photo1-thumb.webp","full":"assets/webp/full/photo1-full.webp"},
  {"id":"photo2","thumb":"assets/webp/thumbs/photo2-thumb.webp","full":"assets/webp/full/photo2-full.webp"},
  {"id":"photo3","thumb":"assets/webp/thumbs/photo3-thumb.webp","full":"assets/webp/full/photo3-full.webp"},
  {"id":"photo4","thumb":"assets/webp/thumbs/photo4-thumb.webp","full":"assets/webp/full/photo4-full.webp"},
  {"id":"photo5","thumb":"assets/webp/thumbs/photo5-thumb.webp","full":"assets/webp/full/photo5-full.webp"},
  {"id":"photo6","thumb":"assets/webp/thumbs/photo6-thumb.webp","full":"assets/webp/full/photo6-full.webp"},
  {"id":"photo7","thumb":"assets/webp/thumbs/photo7-thumb.webp","full":"assets/webp/full/photo7-full.webp"},
  {"id":"photo8","thumb":"assets/webp/thumbs/photo8-thumb.webp","full":"assets/webp/full/photo8-full.webp"},
  {"id":"photo9","thumb":"assets/webp/thumbs/photo9-thumb.webp","full":"assets/webp/full/photo9-full.webp"},
  {"id":"photo10","thumb":"assets/webp/thumbs/photo10-thumb.webp","full":"assets/webp/full/photo10-full.webp"},
  {"id":"photo11","thumb":"assets/webp/thumbs/photo11-thumb.webp","full":"assets/webp/full/photo11-full.webp"},
  {"id":"photo12","thumb":"assets/webp/thumbs/photo12-thumb.webp","full":"assets/webp/full/photo12-full.webp"},
  {"id":"photo13","thumb":"assets/webp/thumbs/photo13-thumb.webp","full":"assets/webp/full/photo13-full.webp"},
  {"id":"photo14","thumb":"assets/webp/thumbs/photo14-thumb.webp","full":"assets/webp/full/photo14-full.webp"},
  {"id":"photo15","thumb":"assets/webp/thumbs/photo15-thumb.webp","full":"assets/webp/full/photo15-full.webp"},
  {"id":"photo16","thumb":"assets/webp/thumbs/photo16-thumb.webp","full":"assets/webp/full/photo16-full.webp"},
  {"id":"photo17","thumb":"assets/webp/thumbs/photo17-thumb.webp","full":"assets/webp/full/photo17-full.webp"},
  {"id":"photo18","thumb":"assets/webp/thumbs/photo18-thumb.webp","full":"assets/webp/full/photo18-full.webp"},
  {"id":"photo19","thumb":"assets/webp/thumbs/photo19-thumb.webp","full":"assets/webp/full/photo19-full.webp"},
  {"id":"photo20","thumb":"assets/webp/thumbs/photo20-thumb.webp","full":"assets/webp/full/photo20-full.webp"},
  {"id":"photo21","thumb":"assets/webp/thumbs/photo21-thumb.webp","full":"assets/webp/full/photo21-full.webp"},
  {"id":"photo22","thumb":"assets/webp/thumbs/photo22-thumb.webp","full":"assets/webp/full/photo22-full.webp"},
  {"id":"photo23","thumb":"assets/webp/thumbs/photo23-thumb.webp","full":"assets/webp/full/photo23-full.webp"},
  {"id":"photo24","thumb":"assets/webp/thumbs/photo24-thumb.webp","full":"assets/webp/full/photo24-full.webp"},
  {"id":"photo25","thumb":"assets/webp/thumbs/photo25-thumb.webp","full":"assets/webp/full/photo25-full.webp"},
  {"id":"photo26","thumb":"assets/webp/thumbs/photo26-thumb.webp","full":"assets/webp/full/photo26-full.webp"},
  {"id":"photo27","thumb":"assets/webp/thumbs/photo27-thumb.webp","full":"assets/webp/full/photo27-full.webp"},
  {"id":"photo28","thumb":"assets/webp/thumbs/photo28-thumb.webp","full":"assets/webp/full/photo28-full.webp"},
  {"id":"photo29","thumb":"assets/webp/thumbs/photo29-thumb.webp","full":"assets/webp/full/photo29-full.webp"},
  {"id":"photo30","thumb":"assets/webp/thumbs/photo30-thumb.webp","full":"assets/webp/full/photo30-full.webp"},
  {"id":"photo31","thumb":"assets/webp/thumbs/photo31-thumb.webp","full":"assets/webp/full/photo31-full.webp"},
  {"id":"photo32","thumb":"assets/webp/thumbs/photo32-thumb.webp","full":"assets/webp/full/photo32-full.webp"},
  {"id":"photo33","thumb":"assets/webp/thumbs/photo33-thumb.webp","full":"assets/webp/full/photo33-full.webp"},
  {"id":"photo34","thumb":"assets/webp/thumbs/photo34-thumb.webp","full":"assets/webp/full/photo34-full.webp"},
  {"id":"photo35","thumb":"assets/webp/thumbs/photo35-thumb.webp","full":"assets/webp/full/photo35-full.webp"},
  {"id":"photo36","thumb":"assets/webp/thumbs/photo36-thumb.webp","full":"assets/webp/full/photo36-full.webp"},
  {"id":"photo37","thumb":"assets/webp/thumbs/photo37-thumb.webp","full":"assets/webp/full/photo37-full.webp"}
]
